fhir_converter/__init__.py
fhir_converter/__main__.py
fhir_converter/exceptions.py
fhir_converter/filters.py
fhir_converter/hl7.py
fhir_converter/loaders.py
fhir_converter/parsers.py
fhir_converter/py.typed
fhir_converter/renderers.py
fhir_converter/tags.py
fhir_converter/templates/ccda/CCD.liquid
fhir_converter/templates/ccda/ConsultationNote.liquid
fhir_converter/templates/ccda/DataType/_Address.liquid
fhir_converter/templates/ccda/DataType/_CodeableConcept.liquid
fhir_converter/templates/ccda/DataType/_Coding.liquid
fhir_converter/templates/ccda/DataType/_ContactPoint.liquid
fhir_converter/templates/ccda/DataType/_HumanName.liquid
fhir_converter/templates/ccda/DataType/_Identifier.liquid
fhir_converter/templates/ccda/DataType/_Period.liquid
fhir_converter/templates/ccda/DischargeSummary.liquid
fhir_converter/templates/ccda/Entry/AdvanceDirective/_entry.liquid
fhir_converter/templates/ccda/Entry/AllergiesAndAdverseReaction/_entry.liquid
fhir_converter/templates/ccda/Entry/AllergiesAndAdverseReaction/_entry_act_entryRelationship.liquid
fhir_converter/templates/ccda/Entry/Complication/_entry.liquid
fhir_converter/templates/ccda/Entry/Encounter/_entry.liquid
fhir_converter/templates/ccda/Entry/Encounter/_entry_encounter_entryRelationship.liquid
fhir_converter/templates/ccda/Entry/Encounter/_entry_encounter_entryRelationship_act_entryRelationship.liquid
fhir_converter/templates/ccda/Entry/Encounter/_entry_encounter_participant.liquid
fhir_converter/templates/ccda/Entry/FamilyHistory/_entry.liquid
fhir_converter/templates/ccda/Entry/FunctionalStatus/_entry.liquid
fhir_converter/templates/ccda/Entry/Goal/_entry.liquid
fhir_converter/templates/ccda/Entry/HealthConcern/_entry.liquid
fhir_converter/templates/ccda/Entry/HealthConcern/_entry_act_entryRelationship.liquid
fhir_converter/templates/ccda/Entry/HospitalAdmissionDiagnosis/_entry.liquid
fhir_converter/templates/ccda/Entry/HospitalAdmissionDiagnosis/_entry_act_entryRelationship.liquid
python_fhir_converter-0.3.0.dist-info/LICENSE
python_fhir_converter-0.3.0.dist-info/METADATA
python_fhir_converter-0.3.0.dist-info/WHEEL
python_fhir_converter-0.3.0.dist-info/entry_points.txt
python_fhir_converter-0.3.0.dist-info/RECORD
