Metadata-Version: 2.1
Name: python-fhir-converter
Version: 0.3.0
Summary: Transformation utility to translate data formats into FHIR
Home-page: https://github.com/chaseastewart/fhir-converter
License: MIT
Author: Chase Stewart
Author-email: chase.a.stewart@outlook.com
Requires-Python: >=3.8.1,<4.0.0
Classifier: Development Status :: 4 - Beta
Classifier: Environment :: Console
Classifier: Intended Audience :: Developers
Classifier: License :: OSI Approved :: MIT License
Classifier: Operating System :: MacOS :: MacOS X
Classifier: Operating System :: POSIX :: Linux
Classifier: Programming Language :: Python
Classifier: Programming Language :: Python :: 3
Classifier: Programming Language :: Python :: 3.9
Classifier: Programming Language :: Python :: 3.10
Classifier: Programming Language :: Python :: 3.11
Classifier: Programming Language :: Python :: 3.12
Classifier: Programming Language :: Python :: 3.8
Classifier: Topic :: Software Development :: Libraries
Requires-Dist: frozendict (==2.3.10)
Requires-Dist: importlib_resources (==6.1.1)
Requires-Dist: isodate (==0.6.1)
Requires-Dist: lxml (==5.3.0)
Requires-Dist: psutil (==5.9.7)
Requires-Dist: pyjson5 (==1.6.5)
Requires-Dist: python-liquid (==1.12.1)
Requires-Dist: typing-extensions (==4.12.2)
Requires-Dist: xmltodict (==0.13.0)
Project-URL: Change Log, https://github.com/chaseastewart/fhir-converter/blob/main/CHANGES.md
Project-URL: Documentation, https://chaseastewart.github.io/fhir-converter/
Project-URL: Issue Tracker, https://github.com/chaseastewart/fhir-converter/issues
Project-URL: Repository, https://github.com/chaseastewart/fhir-converter
